<?xml version="1.0" encoding="UTF-8" ?>
<!DOCTYPE mapper PUBLIC "-//mybatis.org//DTD Mapper 3.0//EN" "http://mybatis.org/dtd/mybatis-3-mapper.dtd" >
<mapper namespace="com.feast.kanjo.entity.Lbm83ChohyokanriMapper" >
  <resultMap id="BaseResultMap" type="com.feast.kanjo.entity.Lbm83Chohyokanri" >
    <!--
      WARNING - @mbggenerated
      This element is automatically generated by MyBatis Generator, do not modify.
      This element was generated on Mon Jan 22 17:43:51 CST 2018.
    -->
    <id column="chohyoshbtsuid" property="chohyoshbtsuid" jdbcType="VARCHAR" />
    <result column="gamenbrui" property="gamenbrui" jdbcType="VARCHAR" />
    <result column="shtsrykcycle1" property="shtsrykcycle1" jdbcType="VARCHAR" />
    <result column="shtsrykcycle2" property="shtsrykcycle2" jdbcType="VARCHAR" />
    <result column="shtsrykcycle3" property="shtsrykcycle3" jdbcType="VARCHAR" />
    <result column="shtsrykcycle4" property="shtsrykcycle4" jdbcType="VARCHAR" />
    <result column="shtsrykcycle5" property="shtsrykcycle5" jdbcType="VARCHAR" />
    <result column="shtsrykcycle6" property="shtsrykcycle6" jdbcType="VARCHAR" />
    <result column="shtsrykcycle7" property="shtsrykcycle7" jdbcType="VARCHAR" />
    <result column="shtsrykcycle8" property="shtsrykcycle8" jdbcType="VARCHAR" />
    <result column="shtsrykcycle9" property="shtsrykcycle9" jdbcType="VARCHAR" />
    <result column="shtsrykcycle10" property="shtsrykcycle10" jdbcType="VARCHAR" />
    <result column="searchitem_flg1" property="searchitemFlg1" jdbcType="VARCHAR" />
    <result column="searchitem_flg2" property="searchitemFlg2" jdbcType="VARCHAR" />
    <result column="searchitem_flg3" property="searchitemFlg3" jdbcType="VARCHAR" />
    <result column="searchitem_flg4" property="searchitemFlg4" jdbcType="VARCHAR" />
    <result column="searchitem_flg5" property="searchitemFlg5" jdbcType="VARCHAR" />
    <result column="searchitem_flg6" property="searchitemFlg6" jdbcType="VARCHAR" />
    <result column="searchitem_flg7" property="searchitemFlg7" jdbcType="VARCHAR" />
    <result column="searchitem_flg8" property="searchitemFlg8" jdbcType="VARCHAR" />
    <result column="searchitem_flg9" property="searchitemFlg9" jdbcType="VARCHAR" />
    <result column="searchitem_flg10" property="searchitemFlg10" jdbcType="VARCHAR" />
    <result column="searchitem_flg11" property="searchitemFlg11" jdbcType="VARCHAR" />
    <result column="searchitem_flg12" property="searchitemFlg12" jdbcType="VARCHAR" />
    <result column="searchitem_flg13" property="searchitemFlg13" jdbcType="VARCHAR" />
    <result column="searchitem_flg14" property="searchitemFlg14" jdbcType="VARCHAR" />
    <result column="searchitem_flg15" property="searchitemFlg15" jdbcType="VARCHAR" />
    <result column="searchitem_flg16" property="searchitemFlg16" jdbcType="VARCHAR" />
    <result column="searchitem_flg17" property="searchitemFlg17" jdbcType="VARCHAR" />
    <result column="searchitem_flg18" property="searchitemFlg18" jdbcType="VARCHAR" />
    <result column="searchitem_flg19" property="searchitemFlg19" jdbcType="VARCHAR" />
    <result column="searchitem_flg20" property="searchitemFlg20" jdbcType="VARCHAR" />
    <result column="fileshbtsu" property="fileshbtsu" jdbcType="VARCHAR" />
    <result column="chohyokj" property="chohyokj" jdbcType="VARCHAR" />
    <result column="chkkengen" property="chkkengen" jdbcType="VARCHAR" />
    <result column="hojikikan" property="hojikikan" jdbcType="NUMERIC" />
    <result column="deldte" property="deldte" jdbcType="TIMESTAMP" />
    <result column="instdte" property="instdte" jdbcType="TIMESTAMP" />
    <result column="instusrid" property="instusrid" jdbcType="VARCHAR" />
    <result column="instprgid" property="instprgid" jdbcType="VARCHAR" />
    <result column="insipaddr" property="insipaddr" jdbcType="VARCHAR" />
    <result column="upddte" property="upddte" jdbcType="TIMESTAMP" />
    <result column="updusrid" property="updusrid" jdbcType="VARCHAR" />
    <result column="updprgid" property="updprgid" jdbcType="VARCHAR" />
    <result column="updipaddr" property="updipaddr" jdbcType="VARCHAR" />
  </resultMap>
  <sql id="Example_Where_Clause" >
    <!--
      WARNING - @mbggenerated
      This element is automatically generated by MyBatis Generator, do not modify.
      This element was generated on Mon Jan 22 17:43:51 CST 2018.
    -->
    <where >
      <foreach collection="oredCriteria" item="criteria" separator="or" >
        <if test="criteria.valid" >
          <trim prefix="(" suffix=")" prefixOverrides="and" >
            <foreach collection="criteria.criteria" item="criterion" >
              <choose >
                <when test="criterion.noValue" >
                  and ${criterion.condition}
                </when>
                <when test="criterion.singleValue" >
                  and ${criterion.condition} #{criterion.value}
                </when>
                <when test="criterion.betweenValue" >
                  and ${criterion.condition} #{criterion.value} and #{criterion.secondValue}
                </when>
                <when test="criterion.listValue" >
                  and ${criterion.condition}
                  <foreach collection="criterion.value" item="listItem" open="(" close=")" separator="," >
                    #{listItem}
                  </foreach>
                </when>
              </choose>
            </foreach>
          </trim>
        </if>
      </foreach>
    </where>
  </sql>
  <sql id="Update_By_Example_Where_Clause" >
    <!--
      WARNING - @mbggenerated
      This element is automatically generated by MyBatis Generator, do not modify.
      This element was generated on Mon Jan 22 17:43:51 CST 2018.
    -->
    <where >
      <foreach collection="example.oredCriteria" item="criteria" separator="or" >
        <if test="criteria.valid" >
          <trim prefix="(" suffix=")" prefixOverrides="and" >
            <foreach collection="criteria.criteria" item="criterion" >
              <choose >
                <when test="criterion.noValue" >
                  and ${criterion.condition}
                </when>
                <when test="criterion.singleValue" >
                  and ${criterion.condition} #{criterion.value}
                </when>
                <when test="criterion.betweenValue" >
                  and ${criterion.condition} #{criterion.value} and #{criterion.secondValue}
                </when>
                <when test="criterion.listValue" >
                  and ${criterion.condition}
                  <foreach collection="criterion.value" item="listItem" open="(" close=")" separator="," >
                    #{listItem}
                  </foreach>
                </when>
              </choose>
            </foreach>
          </trim>
        </if>
      </foreach>
    </where>
  </sql>
  <sql id="Base_Column_List" >
    <!--
      WARNING - @mbggenerated
      This element is automatically generated by MyBatis Generator, do not modify.
      This element was generated on Mon Jan 22 17:43:51 CST 2018.
    -->
    chohyoshbtsuid, gamenbrui, shtsrykcycle1, shtsrykcycle2, shtsrykcycle3, shtsrykcycle4, 
    shtsrykcycle5, shtsrykcycle6, shtsrykcycle7, shtsrykcycle8, shtsrykcycle9, shtsrykcycle10, 
    searchitem_flg1, searchitem_flg2, searchitem_flg3, searchitem_flg4, searchitem_flg5, 
    searchitem_flg6, searchitem_flg7, searchitem_flg8, searchitem_flg9, searchitem_flg10, 
    searchitem_flg11, searchitem_flg12, searchitem_flg13, searchitem_flg14, searchitem_flg15, 
    searchitem_flg16, searchitem_flg17, searchitem_flg18, searchitem_flg19, searchitem_flg20, 
    fileshbtsu, chohyokj, chkkengen, hojikikan, deldte, instdte, instusrid, instprgid, 
    insipaddr, upddte, updusrid, updprgid, updipaddr
  </sql>
  <select id="selectByExample" resultMap="BaseResultMap" parameterType="com.feast.kanjo.entity.Lbm83ChohyokanriExample" >
    <!--
      WARNING - @mbggenerated
      This element is automatically generated by MyBatis Generator, do not modify.
      This element was generated on Mon Jan 22 17:43:51 CST 2018.
    -->
    select
    <if test="distinct" >
      distinct
    </if>
    <include refid="Base_Column_List" />
    from lb01_pt.lbm83_chohyokanri
    <if test="_parameter != null" >
      <include refid="Example_Where_Clause" />
    </if>
    <if test="orderByClause != null" >
      order by ${orderByClause}
    </if>
  </select>
  <select id="selectByPrimaryKey" resultMap="BaseResultMap" parameterType="java.lang.String" >
    <!--
      WARNING - @mbggenerated
      This element is automatically generated by MyBatis Generator, do not modify.
      This element was generated on Mon Jan 22 17:43:51 CST 2018.
    -->
    select 
    <include refid="Base_Column_List" />
    from lb01_pt.lbm83_chohyokanri
    where chohyoshbtsuid = #{chohyoshbtsuid,jdbcType=VARCHAR}
  </select>
  <delete id="deleteByPrimaryKey" parameterType="java.lang.String" >
    <!--
      WARNING - @mbggenerated
      This element is automatically generated by MyBatis Generator, do not modify.
      This element was generated on Mon Jan 22 17:43:51 CST 2018.
    -->
    delete from lb01_pt.lbm83_chohyokanri
    where chohyoshbtsuid = #{chohyoshbtsuid,jdbcType=VARCHAR}
  </delete>
  <delete id="deleteByExample" parameterType="com.feast.kanjo.entity.Lbm83ChohyokanriExample" >
    <!--
      WARNING - @mbggenerated
      This element is automatically generated by MyBatis Generator, do not modify.
      This element was generated on Mon Jan 22 17:43:51 CST 2018.
    -->
    delete from lb01_pt.lbm83_chohyokanri
    <if test="_parameter != null" >
      <include refid="Example_Where_Clause" />
    </if>
  </delete>
  <insert id="insert" parameterType="com.feast.kanjo.entity.Lbm83Chohyokanri" >
    <!--
      WARNING - @mbggenerated
      This element is automatically generated by MyBatis Generator, do not modify.
      This element was generated on Mon Jan 22 17:43:51 CST 2018.
    -->
    insert into lb01_pt.lbm83_chohyokanri (chohyoshbtsuid, gamenbrui, shtsrykcycle1, 
      shtsrykcycle2, shtsrykcycle3, shtsrykcycle4, 
      shtsrykcycle5, shtsrykcycle6, shtsrykcycle7, 
      shtsrykcycle8, shtsrykcycle9, shtsrykcycle10, 
      searchitem_flg1, searchitem_flg2, searchitem_flg3, 
      searchitem_flg4, searchitem_flg5, searchitem_flg6, 
      searchitem_flg7, searchitem_flg8, searchitem_flg9, 
      searchitem_flg10, searchitem_flg11, searchitem_flg12, 
      searchitem_flg13, searchitem_flg14, searchitem_flg15, 
      searchitem_flg16, searchitem_flg17, searchitem_flg18, 
      searchitem_flg19, searchitem_flg20, fileshbtsu, 
      chohyokj, chkkengen, hojikikan, 
      deldte, instdte, instusrid, 
      instprgid, insipaddr, upddte, 
      updusrid, updprgid, updipaddr
      )
    values (#{chohyoshbtsuid,jdbcType=VARCHAR}, #{gamenbrui,jdbcType=VARCHAR}, #{shtsrykcycle1,jdbcType=VARCHAR}, 
      #{shtsrykcycle2,jdbcType=VARCHAR}, #{shtsrykcycle3,jdbcType=VARCHAR}, #{shtsrykcycle4,jdbcType=VARCHAR}, 
      #{shtsrykcycle5,jdbcType=VARCHAR}, #{shtsrykcycle6,jdbcType=VARCHAR}, #{shtsrykcycle7,jdbcType=VARCHAR}, 
      #{shtsrykcycle8,jdbcType=VARCHAR}, #{shtsrykcycle9,jdbcType=VARCHAR}, #{shtsrykcycle10,jdbcType=VARCHAR}, 
      #{searchitemFlg1,jdbcType=VARCHAR}, #{searchitemFlg2,jdbcType=VARCHAR}, #{searchitemFlg3,jdbcType=VARCHAR}, 
      #{searchitemFlg4,jdbcType=VARCHAR}, #{searchitemFlg5,jdbcType=VARCHAR}, #{searchitemFlg6,jdbcType=VARCHAR}, 
      #{searchitemFlg7,jdbcType=VARCHAR}, #{searchitemFlg8,jdbcType=VARCHAR}, #{searchitemFlg9,jdbcType=VARCHAR}, 
      #{searchitemFlg10,jdbcType=VARCHAR}, #{searchitemFlg11,jdbcType=VARCHAR}, #{searchitemFlg12,jdbcType=VARCHAR}, 
      #{searchitemFlg13,jdbcType=VARCHAR}, #{searchitemFlg14,jdbcType=VARCHAR}, #{searchitemFlg15,jdbcType=VARCHAR}, 
      #{searchitemFlg16,jdbcType=VARCHAR}, #{searchitemFlg17,jdbcType=VARCHAR}, #{searchitemFlg18,jdbcType=VARCHAR}, 
      #{searchitemFlg19,jdbcType=VARCHAR}, #{searchitemFlg20,jdbcType=VARCHAR}, #{fileshbtsu,jdbcType=VARCHAR}, 
      #{chohyokj,jdbcType=VARCHAR}, #{chkkengen,jdbcType=VARCHAR}, #{hojikikan,jdbcType=NUMERIC}, 
      #{deldte,jdbcType=TIMESTAMP}, #{instdte,jdbcType=TIMESTAMP}, #{instusrid,jdbcType=VARCHAR}, 
      #{instprgid,jdbcType=VARCHAR}, #{insipaddr,jdbcType=VARCHAR}, #{upddte,jdbcType=TIMESTAMP}, 
      #{updusrid,jdbcType=VARCHAR}, #{updprgid,jdbcType=VARCHAR}, #{updipaddr,jdbcType=VARCHAR}
      )
  </insert>
  <insert id="insertSelective" parameterType="com.feast.kanjo.entity.Lbm83Chohyokanri" >
    <!--
      WARNING - @mbggenerated
      This element is automatically generated by MyBatis Generator, do not modify.
      This element was generated on Mon Jan 22 17:43:51 CST 2018.
    -->
    insert into lb01_pt.lbm83_chohyokanri
    <trim prefix="(" suffix=")" suffixOverrides="," >
      <if test="chohyoshbtsuid != null" >
        chohyoshbtsuid,
      </if>
      <if test="gamenbrui != null" >
        gamenbrui,
      </if>
      <if test="shtsrykcycle1 != null" >
        shtsrykcycle1,
      </if>
      <if test="shtsrykcycle2 != null" >
        shtsrykcycle2,
      </if>
      <if test="shtsrykcycle3 != null" >
        shtsrykcycle3,
      </if>
      <if test="shtsrykcycle4 != null" >
        shtsrykcycle4,
      </if>
      <if test="shtsrykcycle5 != null" >
        shtsrykcycle5,
      </if>
      <if test="shtsrykcycle6 != null" >
        shtsrykcycle6,
      </if>
      <if test="shtsrykcycle7 != null" >
        shtsrykcycle7,
      </if>
      <if test="shtsrykcycle8 != null" >
        shtsrykcycle8,
      </if>
      <if test="shtsrykcycle9 != null" >
        shtsrykcycle9,
      </if>
      <if test="shtsrykcycle10 != null" >
        shtsrykcycle10,
      </if>
      <if test="searchitemFlg1 != null" >
        searchitem_flg1,
      </if>
      <if test="searchitemFlg2 != null" >
        searchitem_flg2,
      </if>
      <if test="searchitemFlg3 != null" >
        searchitem_flg3,
      </if>
      <if test="searchitemFlg4 != null" >
        searchitem_flg4,
      </if>
      <if test="searchitemFlg5 != null" >
        searchitem_flg5,
      </if>
      <if test="searchitemFlg6 != null" >
        searchitem_flg6,
      </if>
      <if test="searchitemFlg7 != null" >
        searchitem_flg7,
      </if>
      <if test="searchitemFlg8 != null" >
        searchitem_flg8,
      </if>
      <if test="searchitemFlg9 != null" >
        searchitem_flg9,
      </if>
      <if test="searchitemFlg10 != null" >
        searchitem_flg10,
      </if>
      <if test="searchitemFlg11 != null" >
        searchitem_flg11,
      </if>
      <if test="searchitemFlg12 != null" >
        searchitem_flg12,
      </if>
      <if test="searchitemFlg13 != null" >
        searchitem_flg13,
      </if>
      <if test="searchitemFlg14 != null" >
        searchitem_flg14,
      </if>
      <if test="searchitemFlg15 != null" >
        searchitem_flg15,
      </if>
      <if test="searchitemFlg16 != null" >
        searchitem_flg16,
      </if>
      <if test="searchitemFlg17 != null" >
        searchitem_flg17,
      </if>
      <if test="searchitemFlg18 != null" >
        searchitem_flg18,
      </if>
      <if test="searchitemFlg19 != null" >
        searchitem_flg19,
      </if>
      <if test="searchitemFlg20 != null" >
        searchitem_flg20,
      </if>
      <if test="fileshbtsu != null" >
        fileshbtsu,
      </if>
      <if test="chohyokj != null" >
        chohyokj,
      </if>
      <if test="chkkengen != null" >
        chkkengen,
      </if>
      <if test="hojikikan != null" >
        hojikikan,
      </if>
      <if test="deldte != null" >
        deldte,
      </if>
      <if test="instdte != null" >
        instdte,
      </if>
      <if test="instusrid != null" >
        instusrid,
      </if>
      <if test="instprgid != null" >
        instprgid,
      </if>
      <if test="insipaddr != null" >
        insipaddr,
      </if>
      <if test="upddte != null" >
        upddte,
      </if>
      <if test="updusrid != null" >
        updusrid,
      </if>
      <if test="updprgid != null" >
        updprgid,
      </if>
      <if test="updipaddr != null" >
        updipaddr,
      </if>
    </trim>
    <trim prefix="values (" suffix=")" suffixOverrides="," >
      <if test="chohyoshbtsuid != null" >
        #{chohyoshbtsuid,jdbcType=VARCHAR},
      </if>
      <if test="gamenbrui != null" >
        #{gamenbrui,jdbcType=VARCHAR},
      </if>
      <if test="shtsrykcycle1 != null" >
        #{shtsrykcycle1,jdbcType=VARCHAR},
      </if>
      <if test="shtsrykcycle2 != null" >
        #{shtsrykcycle2,jdbcType=VARCHAR},
      </if>
      <if test="shtsrykcycle3 != null" >
        #{shtsrykcycle3,jdbcType=VARCHAR},
      </if>
      <if test="shtsrykcycle4 != null" >
        #{shtsrykcycle4,jdbcType=VARCHAR},
      </if>
      <if test="shtsrykcycle5 != null" >
        #{shtsrykcycle5,jdbcType=VARCHAR},
      </if>
      <if test="shtsrykcycle6 != null" >
        #{shtsrykcycle6,jdbcType=VARCHAR},
      </if>
      <if test="shtsrykcycle7 != null" >
        #{shtsrykcycle7,jdbcType=VARCHAR},
      </if>
      <if test="shtsrykcycle8 != null" >
        #{shtsrykcycle8,jdbcType=VARCHAR},
      </if>
      <if test="shtsrykcycle9 != null" >
        #{shtsrykcycle9,jdbcType=VARCHAR},
      </if>
      <if test="shtsrykcycle10 != null" >
        #{shtsrykcycle10,jdbcType=VARCHAR},
      </if>
      <if test="searchitemFlg1 != null" >
        #{searchitemFlg1,jdbcType=VARCHAR},
      </if>
      <if test="searchitemFlg2 != null" >
        #{searchitemFlg2,jdbcType=VARCHAR},
      </if>
      <if test="searchitemFlg3 != null" >
        #{searchitemFlg3,jdbcType=VARCHAR},
      </if>
      <if test="searchitemFlg4 != null" >
        #{searchitemFlg4,jdbcType=VARCHAR},
      </if>
      <if test="searchitemFlg5 != null" >
        #{searchitemFlg5,jdbcType=VARCHAR},
      </if>
      <if test="searchitemFlg6 != null" >
        #{searchitemFlg6,jdbcType=VARCHAR},
      </if>
      <if test="searchitemFlg7 != null" >
        #{searchitemFlg7,jdbcType=VARCHAR},
      </if>
      <if test="searchitemFlg8 != null" >
        #{searchitemFlg8,jdbcType=VARCHAR},
      </if>
      <if test="searchitemFlg9 != null" >
        #{searchitemFlg9,jdbcType=VARCHAR},
      </if>
      <if test="searchitemFlg10 != null" >
        #{searchitemFlg10,jdbcType=VARCHAR},
      </if>
      <if test="searchitemFlg11 != null" >
        #{searchitemFlg11,jdbcType=VARCHAR},
      </if>
      <if test="searchitemFlg12 != null" >
        #{searchitemFlg12,jdbcType=VARCHAR},
      </if>
      <if test="searchitemFlg13 != null" >
        #{searchitemFlg13,jdbcType=VARCHAR},
      </if>
      <if test="searchitemFlg14 != null" >
        #{searchitemFlg14,jdbcType=VARCHAR},
      </if>
      <if test="searchitemFlg15 != null" >
        #{searchitemFlg15,jdbcType=VARCHAR},
      </if>
      <if test="searchitemFlg16 != null" >
        #{searchitemFlg16,jdbcType=VARCHAR},
      </if>
      <if test="searchitemFlg17 != null" >
        #{searchitemFlg17,jdbcType=VARCHAR},
      </if>
      <if test="searchitemFlg18 != null" >
        #{searchitemFlg18,jdbcType=VARCHAR},
      </if>
      <if test="searchitemFlg19 != null" >
        #{searchitemFlg19,jdbcType=VARCHAR},
      </if>
      <if test="searchitemFlg20 != null" >
        #{searchitemFlg20,jdbcType=VARCHAR},
      </if>
      <if test="fileshbtsu != null" >
        #{fileshbtsu,jdbcType=VARCHAR},
      </if>
      <if test="chohyokj != null" >
        #{chohyokj,jdbcType=VARCHAR},
      </if>
      <if test="chkkengen != null" >
        #{chkkengen,jdbcType=VARCHAR},
      </if>
      <if test="hojikikan != null" >
        #{hojikikan,jdbcType=NUMERIC},
      </if>
      <if test="deldte != null" >
        #{deldte,jdbcType=TIMESTAMP},
      </if>
      <if test="instdte != null" >
        #{instdte,jdbcType=TIMESTAMP},
      </if>
      <if test="instusrid != null" >
        #{instusrid,jdbcType=VARCHAR},
      </if>
      <if test="instprgid != null" >
        #{instprgid,jdbcType=VARCHAR},
      </if>
      <if test="insipaddr != null" >
        #{insipaddr,jdbcType=VARCHAR},
      </if>
      <if test="upddte != null" >
        #{upddte,jdbcType=TIMESTAMP},
      </if>
      <if test="updusrid != null" >
        #{updusrid,jdbcType=VARCHAR},
      </if>
      <if test="updprgid != null" >
        #{updprgid,jdbcType=VARCHAR},
      </if>
      <if test="updipaddr != null" >
        #{updipaddr,jdbcType=VARCHAR},
      </if>
    </trim>
  </insert>
  <select id="countByExample" parameterType="com.feast.kanjo.entity.Lbm83ChohyokanriExample" resultType="java.lang.Integer" >
    <!--
      WARNING - @mbggenerated
      This element is automatically generated by MyBatis Generator, do not modify.
      This element was generated on Mon Jan 22 17:43:51 CST 2018.
    -->
    select count(*) from lb01_pt.lbm83_chohyokanri
    <if test="_parameter != null" >
      <include refid="Example_Where_Clause" />
    </if>
  </select>
  <update id="updateByExampleSelective" parameterType="map" >
    <!--
      WARNING - @mbggenerated
      This element is automatically generated by MyBatis Generator, do not modify.
      This element was generated on Mon Jan 22 17:43:51 CST 2018.
    -->
    update lb01_pt.lbm83_chohyokanri
    <set >
      <if test="record.chohyoshbtsuid != null" >
        chohyoshbtsuid = #{record.chohyoshbtsuid,jdbcType=VARCHAR},
      </if>
      <if test="record.gamenbrui != null" >
        gamenbrui = #{record.gamenbrui,jdbcType=VARCHAR},
      </if>
      <if test="record.shtsrykcycle1 != null" >
        shtsrykcycle1 = #{record.shtsrykcycle1,jdbcType=VARCHAR},
      </if>
      <if test="record.shtsrykcycle2 != null" >
        shtsrykcycle2 = #{record.shtsrykcycle2,jdbcType=VARCHAR},
      </if>
      <if test="record.shtsrykcycle3 != null" >
        shtsrykcycle3 = #{record.shtsrykcycle3,jdbcType=VARCHAR},
      </if>
      <if test="record.shtsrykcycle4 != null" >
        shtsrykcycle4 = #{record.shtsrykcycle4,jdbcType=VARCHAR},
      </if>
      <if test="record.shtsrykcycle5 != null" >
        shtsrykcycle5 = #{record.shtsrykcycle5,jdbcType=VARCHAR},
      </if>
      <if test="record.shtsrykcycle6 != null" >
        shtsrykcycle6 = #{record.shtsrykcycle6,jdbcType=VARCHAR},
      </if>
      <if test="record.shtsrykcycle7 != null" >
        shtsrykcycle7 = #{record.shtsrykcycle7,jdbcType=VARCHAR},
      </if>
      <if test="record.shtsrykcycle8 != null" >
        shtsrykcycle8 = #{record.shtsrykcycle8,jdbcType=VARCHAR},
      </if>
      <if test="record.shtsrykcycle9 != null" >
        shtsrykcycle9 = #{record.shtsrykcycle9,jdbcType=VARCHAR},
      </if>
      <if test="record.shtsrykcycle10 != null" >
        shtsrykcycle10 = #{record.shtsrykcycle10,jdbcType=VARCHAR},
      </if>
      <if test="record.searchitemFlg1 != null" >
        searchitem_flg1 = #{record.searchitemFlg1,jdbcType=VARCHAR},
      </if>
      <if test="record.searchitemFlg2 != null" >
        searchitem_flg2 = #{record.searchitemFlg2,jdbcType=VARCHAR},
      </if>
      <if test="record.searchitemFlg3 != null" >
        searchitem_flg3 = #{record.searchitemFlg3,jdbcType=VARCHAR},
      </if>
      <if test="record.searchitemFlg4 != null" >
        searchitem_flg4 = #{record.searchitemFlg4,jdbcType=VARCHAR},
      </if>
      <if test="record.searchitemFlg5 != null" >
        searchitem_flg5 = #{record.searchitemFlg5,jdbcType=VARCHAR},
      </if>
      <if test="record.searchitemFlg6 != null" >
        searchitem_flg6 = #{record.searchitemFlg6,jdbcType=VARCHAR},
      </if>
      <if test="record.searchitemFlg7 != null" >
        searchitem_flg7 = #{record.searchitemFlg7,jdbcType=VARCHAR},
      </if>
      <if test="record.searchitemFlg8 != null" >
        searchitem_flg8 = #{record.searchitemFlg8,jdbcType=VARCHAR},
      </if>
      <if test="record.searchitemFlg9 != null" >
        searchitem_flg9 = #{record.searchitemFlg9,jdbcType=VARCHAR},
      </if>
      <if test="record.searchitemFlg10 != null" >
        searchitem_flg10 = #{record.searchitemFlg10,jdbcType=VARCHAR},
      </if>
      <if test="record.searchitemFlg11 != null" >
        searchitem_flg11 = #{record.searchitemFlg11,jdbcType=VARCHAR},
      </if>
      <if test="record.searchitemFlg12 != null" >
        searchitem_flg12 = #{record.searchitemFlg12,jdbcType=VARCHAR},
      </if>
      <if test="record.searchitemFlg13 != null" >
        searchitem_flg13 = #{record.searchitemFlg13,jdbcType=VARCHAR},
      </if>
      <if test="record.searchitemFlg14 != null" >
        searchitem_flg14 = #{record.searchitemFlg14,jdbcType=VARCHAR},
      </if>
      <if test="record.searchitemFlg15 != null" >
        searchitem_flg15 = #{record.searchitemFlg15,jdbcType=VARCHAR},
      </if>
      <if test="record.searchitemFlg16 != null" >
        searchitem_flg16 = #{record.searchitemFlg16,jdbcType=VARCHAR},
      </if>
      <if test="record.searchitemFlg17 != null" >
        searchitem_flg17 = #{record.searchitemFlg17,jdbcType=VARCHAR},
      </if>
      <if test="record.searchitemFlg18 != null" >
        searchitem_flg18 = #{record.searchitemFlg18,jdbcType=VARCHAR},
      </if>
      <if test="record.searchitemFlg19 != null" >
        searchitem_flg19 = #{record.searchitemFlg19,jdbcType=VARCHAR},
      </if>
      <if test="record.searchitemFlg20 != null" >
        searchitem_flg20 = #{record.searchitemFlg20,jdbcType=VARCHAR},
      </if>
      <if test="record.fileshbtsu != null" >
        fileshbtsu = #{record.fileshbtsu,jdbcType=VARCHAR},
      </if>
      <if test="record.chohyokj != null" >
        chohyokj = #{record.chohyokj,jdbcType=VARCHAR},
      </if>
      <if test="record.chkkengen != null" >
        chkkengen = #{record.chkkengen,jdbcType=VARCHAR},
      </if>
      <if test="record.hojikikan != null" >
        hojikikan = #{record.hojikikan,jdbcType=NUMERIC},
      </if>
      <if test="record.deldte != null" >
        deldte = #{record.deldte,jdbcType=TIMESTAMP},
      </if>
      <if test="record.instdte != null" >
        instdte = #{record.instdte,jdbcType=TIMESTAMP},
      </if>
      <if test="record.instusrid != null" >
        instusrid = #{record.instusrid,jdbcType=VARCHAR},
      </if>
      <if test="record.instprgid != null" >
        instprgid = #{record.instprgid,jdbcType=VARCHAR},
      </if>
      <if test="record.insipaddr != null" >
        insipaddr = #{record.insipaddr,jdbcType=VARCHAR},
      </if>
      <if test="record.upddte != null" >
        upddte = #{record.upddte,jdbcType=TIMESTAMP},
      </if>
      <if test="record.updusrid != null" >
        updusrid = #{record.updusrid,jdbcType=VARCHAR},
      </if>
      <if test="record.updprgid != null" >
        updprgid = #{record.updprgid,jdbcType=VARCHAR},
      </if>
      <if test="record.updipaddr != null" >
        updipaddr = #{record.updipaddr,jdbcType=VARCHAR},
      </if>
    </set>
    <if test="_parameter != null" >
      <include refid="Update_By_Example_Where_Clause" />
    </if>
  </update>
  <update id="updateByExample" parameterType="map" >
    <!--
      WARNING - @mbggenerated
      This element is automatically generated by MyBatis Generator, do not modify.
      This element was generated on Mon Jan 22 17:43:51 CST 2018.
    -->
    update lb01_pt.lbm83_chohyokanri
    set chohyoshbtsuid = #{record.chohyoshbtsuid,jdbcType=VARCHAR},
      gamenbrui = #{record.gamenbrui,jdbcType=VARCHAR},
      shtsrykcycle1 = #{record.shtsrykcycle1,jdbcType=VARCHAR},
      shtsrykcycle2 = #{record.shtsrykcycle2,jdbcType=VARCHAR},
      shtsrykcycle3 = #{record.shtsrykcycle3,jdbcType=VARCHAR},
      shtsrykcycle4 = #{record.shtsrykcycle4,jdbcType=VARCHAR},
      shtsrykcycle5 = #{record.shtsrykcycle5,jdbcType=VARCHAR},
      shtsrykcycle6 = #{record.shtsrykcycle6,jdbcType=VARCHAR},
      shtsrykcycle7 = #{record.shtsrykcycle7,jdbcType=VARCHAR},
      shtsrykcycle8 = #{record.shtsrykcycle8,jdbcType=VARCHAR},
      shtsrykcycle9 = #{record.shtsrykcycle9,jdbcType=VARCHAR},
      shtsrykcycle10 = #{record.shtsrykcycle10,jdbcType=VARCHAR},
      searchitem_flg1 = #{record.searchitemFlg1,jdbcType=VARCHAR},
      searchitem_flg2 = #{record.searchitemFlg2,jdbcType=VARCHAR},
      searchitem_flg3 = #{record.searchitemFlg3,jdbcType=VARCHAR},
      searchitem_flg4 = #{record.searchitemFlg4,jdbcType=VARCHAR},
      searchitem_flg5 = #{record.searchitemFlg5,jdbcType=VARCHAR},
      searchitem_flg6 = #{record.searchitemFlg6,jdbcType=VARCHAR},
      searchitem_flg7 = #{record.searchitemFlg7,jdbcType=VARCHAR},
      searchitem_flg8 = #{record.searchitemFlg8,jdbcType=VARCHAR},
      searchitem_flg9 = #{record.searchitemFlg9,jdbcType=VARCHAR},
      searchitem_flg10 = #{record.searchitemFlg10,jdbcType=VARCHAR},
      searchitem_flg11 = #{record.searchitemFlg11,jdbcType=VARCHAR},
      searchitem_flg12 = #{record.searchitemFlg12,jdbcType=VARCHAR},
      searchitem_flg13 = #{record.searchitemFlg13,jdbcType=VARCHAR},
      searchitem_flg14 = #{record.searchitemFlg14,jdbcType=VARCHAR},
      searchitem_flg15 = #{record.searchitemFlg15,jdbcType=VARCHAR},
      searchitem_flg16 = #{record.searchitemFlg16,jdbcType=VARCHAR},
      searchitem_flg17 = #{record.searchitemFlg17,jdbcType=VARCHAR},
      searchitem_flg18 = #{record.searchitemFlg18,jdbcType=VARCHAR},
      searchitem_flg19 = #{record.searchitemFlg19,jdbcType=VARCHAR},
      searchitem_flg20 = #{record.searchitemFlg20,jdbcType=VARCHAR},
      fileshbtsu = #{record.fileshbtsu,jdbcType=VARCHAR},
      chohyokj = #{record.chohyokj,jdbcType=VARCHAR},
      chkkengen = #{record.chkkengen,jdbcType=VARCHAR},
      hojikikan = #{record.hojikikan,jdbcType=NUMERIC},
      deldte = #{record.deldte,jdbcType=TIMESTAMP},
      instdte = #{record.instdte,jdbcType=TIMESTAMP},
      instusrid = #{record.instusrid,jdbcType=VARCHAR},
      instprgid = #{record.instprgid,jdbcType=VARCHAR},
      insipaddr = #{record.insipaddr,jdbcType=VARCHAR},
      upddte = #{record.upddte,jdbcType=TIMESTAMP},
      updusrid = #{record.updusrid,jdbcType=VARCHAR},
      updprgid = #{record.updprgid,jdbcType=VARCHAR},
      updipaddr = #{record.updipaddr,jdbcType=VARCHAR}
    <if test="_parameter != null" >
      <include refid="Update_By_Example_Where_Clause" />
    </if>
  </update>
  <update id="updateByPrimaryKeySelective" parameterType="com.feast.kanjo.entity.Lbm83Chohyokanri" >
    <!--
      WARNING - @mbggenerated
      This element is automatically generated by MyBatis Generator, do not modify.
      This element was generated on Mon Jan 22 17:43:51 CST 2018.
    -->
    update lb01_pt.lbm83_chohyokanri
    <set >
      <if test="gamenbrui != null" >
        gamenbrui = #{gamenbrui,jdbcType=VARCHAR},
      </if>
      <if test="shtsrykcycle1 != null" >
        shtsrykcycle1 = #{shtsrykcycle1,jdbcType=VARCHAR},
      </if>
      <if test="shtsrykcycle2 != null" >
        shtsrykcycle2 = #{shtsrykcycle2,jdbcType=VARCHAR},
      </if>
      <if test="shtsrykcycle3 != null" >
        shtsrykcycle3 = #{shtsrykcycle3,jdbcType=VARCHAR},
      </if>
      <if test="shtsrykcycle4 != null" >
        shtsrykcycle4 = #{shtsrykcycle4,jdbcType=VARCHAR},
      </if>
      <if test="shtsrykcycle5 != null" >
        shtsrykcycle5 = #{shtsrykcycle5,jdbcType=VARCHAR},
      </if>
      <if test="shtsrykcycle6 != null" >
        shtsrykcycle6 = #{shtsrykcycle6,jdbcType=VARCHAR},
      </if>
      <if test="shtsrykcycle7 != null" >
        shtsrykcycle7 = #{shtsrykcycle7,jdbcType=VARCHAR},
      </if>
      <if test="shtsrykcycle8 != null" >
        shtsrykcycle8 = #{shtsrykcycle8,jdbcType=VARCHAR},
      </if>
      <if test="shtsrykcycle9 != null" >
        shtsrykcycle9 = #{shtsrykcycle9,jdbcType=VARCHAR},
      </if>
      <if test="shtsrykcycle10 != null" >
        shtsrykcycle10 = #{shtsrykcycle10,jdbcType=VARCHAR},
      </if>
      <if test="searchitemFlg1 != null" >
        searchitem_flg1 = #{searchitemFlg1,jdbcType=VARCHAR},
      </if>
      <if test="searchitemFlg2 != null" >
        searchitem_flg2 = #{searchitemFlg2,jdbcType=VARCHAR},
      </if>
      <if test="searchitemFlg3 != null" >
        searchitem_flg3 = #{searchitemFlg3,jdbcType=VARCHAR},
      </if>
      <if test="searchitemFlg4 != null" >
        searchitem_flg4 = #{searchitemFlg4,jdbcType=VARCHAR},
      </if>
      <if test="searchitemFlg5 != null" >
        searchitem_flg5 = #{searchitemFlg5,jdbcType=VARCHAR},
      </if>
      <if test="searchitemFlg6 != null" >
        searchitem_flg6 = #{searchitemFlg6,jdbcType=VARCHAR},
      </if>
      <if test="searchitemFlg7 != null" >
        searchitem_flg7 = #{searchitemFlg7,jdbcType=VARCHAR},
      </if>
      <if test="searchitemFlg8 != null" >
        searchitem_flg8 = #{searchitemFlg8,jdbcType=VARCHAR},
      </if>
      <if test="searchitemFlg9 != null" >
        searchitem_flg9 = #{searchitemFlg9,jdbcType=VARCHAR},
      </if>
      <if test="searchitemFlg10 != null" >
        searchitem_flg10 = #{searchitemFlg10,jdbcType=VARCHAR},
      </if>
      <if test="searchitemFlg11 != null" >
        searchitem_flg11 = #{searchitemFlg11,jdbcType=VARCHAR},
      </if>
      <if test="searchitemFlg12 != null" >
        searchitem_flg12 = #{searchitemFlg12,jdbcType=VARCHAR},
      </if>
      <if test="searchitemFlg13 != null" >
        searchitem_flg13 = #{searchitemFlg13,jdbcType=VARCHAR},
      </if>
      <if test="searchitemFlg14 != null" >
        searchitem_flg14 = #{searchitemFlg14,jdbcType=VARCHAR},
      </if>
      <if test="searchitemFlg15 != null" >
        searchitem_flg15 = #{searchitemFlg15,jdbcType=VARCHAR},
      </if>
      <if test="searchitemFlg16 != null" >
        searchitem_flg16 = #{searchitemFlg16,jdbcType=VARCHAR},
      </if>
      <if test="searchitemFlg17 != null" >
        searchitem_flg17 = #{searchitemFlg17,jdbcType=VARCHAR},
      </if>
      <if test="searchitemFlg18 != null" >
        searchitem_flg18 = #{searchitemFlg18,jdbcType=VARCHAR},
      </if>
      <if test="searchitemFlg19 != null" >
        searchitem_flg19 = #{searchitemFlg19,jdbcType=VARCHAR},
      </if>
      <if test="searchitemFlg20 != null" >
        searchitem_flg20 = #{searchitemFlg20,jdbcType=VARCHAR},
      </if>
      <if test="fileshbtsu != null" >
        fileshbtsu = #{fileshbtsu,jdbcType=VARCHAR},
      </if>
      <if test="chohyokj != null" >
        chohyokj = #{chohyokj,jdbcType=VARCHAR},
      </if>
      <if test="chkkengen != null" >
        chkkengen = #{chkkengen,jdbcType=VARCHAR},
      </if>
      <if test="hojikikan != null" >
        hojikikan = #{hojikikan,jdbcType=NUMERIC},
      </if>
      <if test="deldte != null" >
        deldte = #{deldte,jdbcType=TIMESTAMP},
      </if>
      <if test="instdte != null" >
        instdte = #{instdte,jdbcType=TIMESTAMP},
      </if>
      <if test="instusrid != null" >
        instusrid = #{instusrid,jdbcType=VARCHAR},
      </if>
      <if test="instprgid != null" >
        instprgid = #{instprgid,jdbcType=VARCHAR},
      </if>
      <if test="insipaddr != null" >
        insipaddr = #{insipaddr,jdbcType=VARCHAR},
      </if>
      <if test="upddte != null" >
        upddte = #{upddte,jdbcType=TIMESTAMP},
      </if>
      <if test="updusrid != null" >
        updusrid = #{updusrid,jdbcType=VARCHAR},
      </if>
      <if test="updprgid != null" >
        updprgid = #{updprgid,jdbcType=VARCHAR},
      </if>
      <if test="updipaddr != null" >
        updipaddr = #{updipaddr,jdbcType=VARCHAR},
      </if>
    </set>
    where chohyoshbtsuid = #{chohyoshbtsuid,jdbcType=VARCHAR}
  </update>
  <update id="updateByPrimaryKey" parameterType="com.feast.kanjo.entity.Lbm83Chohyokanri" >
    <!--
      WARNING - @mbggenerated
      This element is automatically generated by MyBatis Generator, do not modify.
      This element was generated on Mon Jan 22 17:43:51 CST 2018.
    -->
    update lb01_pt.lbm83_chohyokanri
    set gamenbrui = #{gamenbrui,jdbcType=VARCHAR},
      shtsrykcycle1 = #{shtsrykcycle1,jdbcType=VARCHAR},
      shtsrykcycle2 = #{shtsrykcycle2,jdbcType=VARCHAR},
      shtsrykcycle3 = #{shtsrykcycle3,jdbcType=VARCHAR},
      shtsrykcycle4 = #{shtsrykcycle4,jdbcType=VARCHAR},
      shtsrykcycle5 = #{shtsrykcycle5,jdbcType=VARCHAR},
      shtsrykcycle6 = #{shtsrykcycle6,jdbcType=VARCHAR},
      shtsrykcycle7 = #{shtsrykcycle7,jdbcType=VARCHAR},
      shtsrykcycle8 = #{shtsrykcycle8,jdbcType=VARCHAR},
      shtsrykcycle9 = #{shtsrykcycle9,jdbcType=VARCHAR},
      shtsrykcycle10 = #{shtsrykcycle10,jdbcType=VARCHAR},
      searchitem_flg1 = #{searchitemFlg1,jdbcType=VARCHAR},
      searchitem_flg2 = #{searchitemFlg2,jdbcType=VARCHAR},
      searchitem_flg3 = #{searchitemFlg3,jdbcType=VARCHAR},
      searchitem_flg4 = #{searchitemFlg4,jdbcType=VARCHAR},
      searchitem_flg5 = #{searchitemFlg5,jdbcType=VARCHAR},
      searchitem_flg6 = #{searchitemFlg6,jdbcType=VARCHAR},
      searchitem_flg7 = #{searchitemFlg7,jdbcType=VARCHAR},
      searchitem_flg8 = #{searchitemFlg8,jdbcType=VARCHAR},
      searchitem_flg9 = #{searchitemFlg9,jdbcType=VARCHAR},
      searchitem_flg10 = #{searchitemFlg10,jdbcType=VARCHAR},
      searchitem_flg11 = #{searchitemFlg11,jdbcType=VARCHAR},
      searchitem_flg12 = #{searchitemFlg12,jdbcType=VARCHAR},
      searchitem_flg13 = #{searchitemFlg13,jdbcType=VARCHAR},
      searchitem_flg14 = #{searchitemFlg14,jdbcType=VARCHAR},
      searchitem_flg15 = #{searchitemFlg15,jdbcType=VARCHAR},
      searchitem_flg16 = #{searchitemFlg16,jdbcType=VARCHAR},
      searchitem_flg17 = #{searchitemFlg17,jdbcType=VARCHAR},
      searchitem_flg18 = #{searchitemFlg18,jdbcType=VARCHAR},
      searchitem_flg19 = #{searchitemFlg19,jdbcType=VARCHAR},
      searchitem_flg20 = #{searchitemFlg20,jdbcType=VARCHAR},
      fileshbtsu = #{fileshbtsu,jdbcType=VARCHAR},
      chohyokj = #{chohyokj,jdbcType=VARCHAR},
      chkkengen = #{chkkengen,jdbcType=VARCHAR},
      hojikikan = #{hojikikan,jdbcType=NUMERIC},
      deldte = #{deldte,jdbcType=TIMESTAMP},
      instdte = #{instdte,jdbcType=TIMESTAMP},
      instusrid = #{instusrid,jdbcType=VARCHAR},
      instprgid = #{instprgid,jdbcType=VARCHAR},
      insipaddr = #{insipaddr,jdbcType=VARCHAR},
      upddte = #{upddte,jdbcType=TIMESTAMP},
      updusrid = #{updusrid,jdbcType=VARCHAR},
      updprgid = #{updprgid,jdbcType=VARCHAR},
      updipaddr = #{updipaddr,jdbcType=VARCHAR}
    where chohyoshbtsuid = #{chohyoshbtsuid,jdbcType=VARCHAR}
  </update>
</mapper>